{
"meta":{"test_sets":[],"test_metrics":[],"learn_metrics":[{"best_value":"Min","name":"Logloss"}],"launch_mode":"Train","parameters":"","iteration_count":100,"learn_sets":["learn"],"name":"experiment"},
"iterations":[
{"learn":[0.6838326758],"iteration":0,"passed_time":0.005163148303,"remaining_time":0.511151682},
{"learn":[0.6746180722],"iteration":1,"passed_time":0.009694203094,"remaining_time":0.4750159516},
{"learn":[0.6656156854],"iteration":2,"passed_time":0.01407104832,"remaining_time":0.4549638958},
{"learn":[0.6567823699],"iteration":3,"passed_time":0.01778248205,"remaining_time":0.4267795693},
{"learn":[0.6481274615],"iteration":4,"passed_time":0.02265024708,"remaining_time":0.4303546946},
{"learn":[0.6396290333],"iteration":5,"passed_time":0.02699480703,"remaining_time":0.4229186435},
{"learn":[0.631294828],"iteration":6,"passed_time":0.03174170509,"remaining_time":0.4217112248},
{"learn":[0.6231174197],"iteration":7,"passed_time":0.03608450093,"remaining_time":0.4149717607},
{"learn":[0.615094646],"iteration":8,"passed_time":0.04153967073,"remaining_time":0.4200122263},
{"learn":[0.6072261944],"iteration":9,"passed_time":0.04673742518,"remaining_time":0.4206368266},
{"learn":[0.5994861381],"iteration":10,"passed_time":0.05072113345,"remaining_time":0.4103800797},
{"learn":[0.5918975385],"iteration":11,"passed_time":0.05643428447,"remaining_time":0.4138514194},
{"learn":[0.5844532096],"iteration":12,"passed_time":0.06081224107,"remaining_time":0.4069742287},
{"learn":[0.5771368021],"iteration":13,"passed_time":0.06571357923,"remaining_time":0.4036691296},
{"learn":[0.5700039828],"iteration":14,"passed_time":0.07032690585,"remaining_time":0.3985191332},
{"learn":[0.5629473752],"iteration":15,"passed_time":0.07577933016,"remaining_time":0.3978414833},
{"learn":[0.5560072827],"iteration":16,"passed_time":0.07969941038,"remaining_time":0.3891206507},
{"learn":[0.549196571],"iteration":17,"passed_time":0.08474911447,"remaining_time":0.3860792993},
{"learn":[0.5424978521],"iteration":18,"passed_time":0.08922206378,"remaining_time":0.3803677456},
{"learn":[0.5359217276],"iteration":19,"passed_time":0.09423110306,"remaining_time":0.3769244122},
{"learn":[0.5294486537],"iteration":20,"passed_time":0.09800146419,"remaining_time":0.3686721748},
{"learn":[0.5230937634],"iteration":21,"passed_time":0.1028935909,"remaining_time":0.3648045494},
{"learn":[0.5168460761],"iteration":22,"passed_time":0.1079611165,"remaining_time":0.3614350422},
{"learn":[0.5107024951],"iteration":23,"passed_time":0.1128167281,"remaining_time":0.3572529722},
{"learn":[0.5046618261],"iteration":24,"passed_time":0.1182576644,"remaining_time":0.3547729931},
{"learn":[0.4987171697],"iteration":25,"passed_time":0.1227385422,"remaining_time":0.3493327738},
{"learn":[0.4928732972],"iteration":26,"passed_time":0.1268691934,"remaining_time":0.343016708},
{"learn":[0.4871286587],"iteration":27,"passed_time":0.1306546096,"remaining_time":0.3359689961},
{"learn":[0.4815046316],"iteration":28,"passed_time":0.1357533769,"remaining_time":0.3323617158},
{"learn":[0.4759407986],"iteration":29,"passed_time":0.141251077,"remaining_time":0.3295858464},
{"learn":[0.470468949],"iteration":30,"passed_time":0.1453999607,"remaining_time":0.3236321707},
{"learn":[0.4651218898],"iteration":31,"passed_time":0.1508621159,"remaining_time":0.3205819963},
{"learn":[0.4598134001],"iteration":32,"passed_time":0.1551554965,"remaining_time":0.3150126748},
{"learn":[0.4545894334],"iteration":33,"passed_time":0.1592436587,"remaining_time":0.3091200433},
{"learn":[0.4494445199],"iteration":34,"passed_time":0.163102035,"remaining_time":0.3029037793},
{"learn":[0.4443801492],"iteration":35,"passed_time":0.1686194387,"remaining_time":0.299767891},
{"learn":[0.4394060318],"iteration":36,"passed_time":0.1729835956,"remaining_time":0.2945396357},
{"learn":[0.4345061431],"iteration":37,"passed_time":0.1769887542,"remaining_time":0.2887711252},
{"learn":[0.4296814356],"iteration":38,"passed_time":0.1819840301,"remaining_time":0.2846416882},
{"learn":[0.4249269354],"iteration":39,"passed_time":0.1878195929,"remaining_time":0.2817293894},
{"learn":[0.4202502305],"iteration":40,"passed_time":0.1929132696,"remaining_time":0.2776069001},
{"learn":[0.4156423861],"iteration":41,"passed_time":0.1980482874,"remaining_time":0.2734952541},
{"learn":[0.4111002489],"iteration":42,"passed_time":0.2027897291,"remaining_time":0.2688142921},
{"learn":[0.406632952],"iteration":43,"passed_time":0.2072364008,"remaining_time":0.2637554192},
{"learn":[0.4022320297],"iteration":44,"passed_time":0.2123797432,"remaining_time":0.2595752417},
{"learn":[0.3978891722],"iteration":45,"passed_time":0.2170044227,"remaining_time":0.2547443223},
{"learn":[0.3936162203],"iteration":46,"passed_time":0.2222483396,"remaining_time":0.2506204681},
{"learn":[0.3894006987],"iteration":47,"passed_time":0.2265024122,"remaining_time":0.2453776132},
{"learn":[0.3852746196],"iteration":48,"passed_time":0.2304504087,"remaining_time":0.2398565479},
{"learn":[0.3811841842],"iteration":49,"passed_time":0.2350360508,"remaining_time":0.2350360508},
{"learn":[0.3771505484],"iteration":50,"passed_time":0.2389355318,"remaining_time":0.2295655109},
{"learn":[0.3731730976],"iteration":51,"passed_time":0.2430469694,"remaining_time":0.2243510487},
{"learn":[0.3692665376],"iteration":52,"passed_time":0.2473754215,"remaining_time":0.2193706568},
{"learn":[0.3654447413],"iteration":53,"passed_time":0.2521251862,"remaining_time":0.2147733068},
{"learn":[0.3616490254],"iteration":54,"passed_time":0.2568495217,"remaining_time":0.2101496086},
{"learn":[0.3578977742],"iteration":55,"passed_time":0.2607090006,"remaining_time":0.2048427862},
{"learn":[0.3542063082],"iteration":56,"passed_time":0.2660529207,"remaining_time":0.2007065893},
{"learn":[0.3505705723],"iteration":57,"passed_time":0.2710981042,"remaining_time":0.1963124203},
{"learn":[0.3469869524],"iteration":58,"passed_time":0.2763347548,"remaining_time":0.1920292364},
{"learn":[0.3434556141],"iteration":59,"passed_time":0.2817837196,"remaining_time":0.187855813},
{"learn":[0.339974083],"iteration":60,"passed_time":0.286546505,"remaining_time":0.1832018638},
{"learn":[0.3365393379],"iteration":61,"passed_time":0.2921970594,"remaining_time":0.1790885203},
{"learn":[0.3331480029],"iteration":62,"passed_time":0.2965482652,"remaining_time":0.1741632668},
{"learn":[0.3297993962],"iteration":63,"passed_time":0.3009023871,"remaining_time":0.1692575928},
{"learn":[0.3265012867],"iteration":64,"passed_time":0.3058413129,"remaining_time":0.1646837839},
{"learn":[0.3232484713],"iteration":65,"passed_time":0.3106815586,"remaining_time":0.1600480757},
{"learn":[0.3200382021],"iteration":66,"passed_time":0.3153687478,"remaining_time":0.1553308758},
{"learn":[0.3168786317],"iteration":67,"passed_time":0.3202302919,"remaining_time":0.150696608},
{"learn":[0.3137635262],"iteration":68,"passed_time":0.3250386232,"remaining_time":0.1460318452},
{"learn":[0.3106931663],"iteration":69,"passed_time":0.3303546483,"remaining_time":0.1415805636},
{"learn":[0.3076528343],"iteration":70,"passed_time":0.3346307146,"remaining_time":0.136680151},
{"learn":[0.3046630546],"iteration":71,"passed_time":0.3393173761,"remaining_time":0.1319567574},
{"learn":[0.3017062337],"iteration":72,"passed_time":0.3432179509,"remaining_time":0.1269436257},
{"learn":[0.2988099328],"iteration":73,"passed_time":0.3476460168,"remaining_time":0.1221458978},
{"learn":[0.2959445469],"iteration":74,"passed_time":0.3528242657,"remaining_time":0.1176080886},
{"learn":[0.2931188206],"iteration":75,"passed_time":0.3568903564,"remaining_time":0.1127022178},
{"learn":[0.2903178042],"iteration":76,"passed_time":0.3618852979,"remaining_time":0.1080956085},
{"learn":[0.2875781251],"iteration":77,"passed_time":0.3665402616,"remaining_time":0.1033831507},
{"learn":[0.2848545882],"iteration":78,"passed_time":0.370550482,"remaining_time":0.09850076105},
{"learn":[0.2821655689],"iteration":79,"passed_time":0.3748493054,"remaining_time":0.09371232634},
{"learn":[0.2795112095],"iteration":80,"passed_time":0.3795281043,"remaining_time":0.08902511089},
{"learn":[0.2769000671],"iteration":81,"passed_time":0.3843223628,"remaining_time":0.0843634455},
{"learn":[0.2743168808],"iteration":82,"passed_time":0.3885105482,"remaining_time":0.07957444962},
{"learn":[0.2717670251],"iteration":83,"passed_time":0.3928995821,"remaining_time":0.07483801564},
{"learn":[0.269261007],"iteration":84,"passed_time":0.3976915152,"remaining_time":0.07018085562},
{"learn":[0.26677698],"iteration":85,"passed_time":0.4016506364,"remaining_time":0.06538498732},
{"learn":[0.2643611632],"iteration":86,"passed_time":0.4057772485,"remaining_time":0.06063338196},
{"learn":[0.2619416152],"iteration":87,"passed_time":0.410677985,"remaining_time":0.0560015434},
{"learn":[0.2595691437],"iteration":88,"passed_time":0.4164720334,"remaining_time":0.05147407154},
{"learn":[0.2572143995],"iteration":89,"passed_time":0.4204893503,"remaining_time":0.04672103892},
{"learn":[0.2549018363],"iteration":90,"passed_time":0.4255322346,"remaining_time":0.04208560562},
{"learn":[0.2526191142],"iteration":91,"passed_time":0.431178704,"remaining_time":0.03749380035},
{"learn":[0.250351906],"iteration":92,"passed_time":0.4352783229,"remaining_time":0.03276288452},
{"learn":[0.2481257712],"iteration":93,"passed_time":0.4402228016,"remaining_time":0.02809932776},
{"learn":[0.2459294343],"iteration":94,"passed_time":0.445860117,"remaining_time":0.02346632195},
{"learn":[0.2437664159],"iteration":95,"passed_time":0.4500460972,"remaining_time":0.01875192072},
{"learn":[0.241616883],"iteration":96,"passed_time":0.4538616938,"remaining_time":0.0140369596},
{"learn":[0.2394992787],"iteration":97,"passed_time":0.4583559428,"remaining_time":0.009354202915},
{"learn":[0.2374171863],"iteration":98,"passed_time":0.4640292907,"remaining_time":0.004687164553},
{"learn":[0.2353516203],"iteration":99,"passed_time":0.4680640884,"remaining_time":0}
]}